fastapi_idempotent/__init__.py
fastapi_idempotent/idempotent.py
fastapi_idempotent/kvstorage/__init__.py
fastapi_idempotent/kvstorage/base.py
fastapi_idempotent/kvstorage/memory.py
fastapi_idempotent/kvstorage/redis.py
fastapi_idempotent-0.0.3.dist-info/LICENCE.txt
fastapi_idempotent-0.0.3.dist-info/METADATA
fastapi_idempotent-0.0.3.dist-info/WHEEL
fastapi_idempotent-0.0.3.dist-info/top_level.txt
fastapi_idempotent-0.0.3.dist-info/RECORD
