Metadata-Version: 2.1
Name: fastapi-idempotent
Version: 0.0.3
Summary: API Idempotent requests
Author: Gin1632
Author-email: vothien1632@gmail.com
Keywords: fastapi-idempotent
Classifier: Development Status :: 1 - Planning
Classifier: Intended Audience :: Developers
Classifier: Programming Language :: Python :: 3
Classifier: Operating System :: Unix
Classifier: Operating System :: MacOS :: MacOS X
Classifier: Operating System :: Microsoft :: Windows
License-File: LICENCE.txt
Requires-Dist: starlette (>=0.19.1)
Requires-Dist: pydantic
Requires-Dist: aioredis
